takens_similarity/__init__.py
takens_similarity/embedding.py
takens_similarity/similarity.py
takens_similarity-0.2.0.dist-info/METADATA
takens_similarity-0.2.0.dist-info/WHEEL
takens_similarity-0.2.0.dist-info/top_level.txt
takens_similarity-0.2.0.dist-info/RECORD
