Metadata-Version: 2.4
Name: takens-similarity
Version: 0.2.0
Summary: Core Takens embeddings & similarity tools for time-series
Author-email: Lawrence Ayim <law.ayim@gmail.com>
Project-URL: Homepage, https://github.com/L-Ayim/Takens-Similarity
Project-URL: Source, https://github.com/L-Ayim/Takens-Similarity
Keywords: takens,time-series,similarity,embedding
Classifier: Programming Language :: Python :: 3
Classifier: License :: OSI Approved :: MIT License
Classifier: Operating System :: OS Independent
Requires-Python: >=3.8
Requires-Dist: numpy>=1.20
Requires-Dist: scipy
